AlComplex/__init__.py
AlComplex/mult_val_fun_plot.py
AlComplex-1.0.3.dist-info/METADATA
AlComplex-1.0.3.dist-info/RECORD
AlComplex-1.0.3.dist-info/WHEEL
AlComplex-1.0.3.dist-info/top_level.txt
test/__init__.py
test/test_AlComplex.py
