Metadata-Version: 2.1
Name: AlComplex
Version: 1.0.3
Summary: An extended Complex number library
Home-page: https://github.com/Jexan/AlComplex
Author: Jean Franco Gómez
Author-email: JeanFGomezR@gmail.com
License: MIT
Platform: UNKNOWN
